pytest_history/__init__.py
pytest_history/cli.py
pytest_history/model.py
pytest_history/queries.py
pytest_history/report.py
pytest_history-0.3.0.dist-info/METADATA
pytest_history-0.3.0.dist-info/WHEEL
pytest_history-0.3.0.dist-info/entry_points.txt
pytest_history-0.3.0.dist-info/RECORD
