Metadata-Version: 2.1
Name: pytest-history
Version: 0.3.0
Summary: Pytest plugin to keep a history of your pytest runs
Home-page: https://github.com/Nicoretti/one-piece/tree/grand-line/python/pytest-history
License: MIT
Keywords: pytest,sqlite,sql,history
Author: Nicola Coretti
Author-email: nico.coretti@gmail.com
Requires-Python: >=3.8,<4.0
Classifier: Framework :: Pytest
Classifier: License :: OSI Approved :: MIT License
Classifier: Programming Language :: Python
Classifier: Programming Language :: Python :: 3
Classifier: Programming Language :: Python :: 3.8
Classifier: Programming Language :: Python :: 3.9
Classifier: Programming Language :: Python :: 3.10
Classifier: Programming Language :: Python :: 3.11
Classifier: Topic :: Software Development :: Testing
Requires-Dist: pytest (>=7.4.3,<8.0.0)
Project-URL: Repository, https://github.com/Nicoretti/one-piece/tree/grand-line/python/pytest-history
